src/__init__.py
src/data_prep_kit.py
dataperpkit-0.6.0.dist-info/LICENSE
dataperpkit-0.6.0.dist-info/METADATA
dataperpkit-0.6.0.dist-info/WHEEL
dataperpkit-0.6.0.dist-info/entry_points.txt
dataperpkit-0.6.0.dist-info/top_level.txt
dataperpkit-0.6.0.dist-info/RECORD
