Metadata-Version: 2.1
Name: dataperpkit
Version: 0.6.0
Summary: DataPrepKit is a Python class for data preparation and analysis. It provides functionalities for reading various data formats, summarizing statistics, handling missing values, and encoding categorical data.
Home-page: https://github.com/ahmed-eldesoky284/dataperpkit
Author: Ahmed Eldesoky
Author-email: ahmedeldesoky284@gmail.com
Classifier: Programming Language :: Python :: 3
Classifier: License :: OSI Approved :: MIT License
Classifier: Operating System :: OS Independent
License-File: LICENSE
Requires-Dist: numpy
Requires-Dist: pandas
